pycounts_j99thoms/__init__.py
pycounts_j99thoms/plotting.py
pycounts_j99thoms/pycounts.py
pycounts_j99thoms-0.1.0.dist-info/LICENSE
pycounts_j99thoms-0.1.0.dist-info/METADATA
pycounts_j99thoms-0.1.0.dist-info/WHEEL
pycounts_j99thoms-0.1.0.dist-info/RECORD
